Codes/ALU_32b/ALU_32b.v
//This is the module for 32 bit ALU
module ALU_32b #(parameter w = 16)
                
                (output reg [w-1:0] y,   // ALU 16-bit outputs
                             
                 input [w-1:0] A, B,        // ALU 16-bit inputs
                 
                 input [1:0] Op,           // ALU_Op
                 
                 input clk, reset);
                 
        
         always @(posedge clk, posedge reset)
         	
           begin if (reset == 0) y <= 16'h00000000;  
                else
              case (Op)
               2'b00:  y <= A + B;         // Addition
               
               2'b01:  y <= A - B;         // Subtraction
                
               2'b10:  y <= A & B;         // Bitwise AND
               
               2'b11:  y <= A || B;       // Bitwise OR  
              endcase   
           end


endmodule

ALU_32b/ALU_32b_testbench.v
`timescale 1ns / 1ns
module ALU_32b_testbench;
    reg [15:0] A, B;
    reg [1:0] Op;
    reg clk, reset;
    wire [15:0] y;
    
    
    initial clk = 1;
    always
    	#10 clk = ~clk;

    	
 ALU_32b ALU1(y, A, B, clk, reset, Op);
    initial
        begin
            $dumpfile ("ALU_testbench.vcd");
            $dumpvars (0, ALU_32b_testbench);
            #0 A = 16'h0;
            #0 B = 16'h0;  Op = 2'b11;
            
            #10 A = 16'h0; Op = 2'b00;
            
            #15 B = 16'h0; Op = 2'b01;
            
            #20 Op = 2'b10;
            
            #30 Op = 2'b11;    
            #100 $stop;
            $finish ;
        end
    
endmodule

Codes/ALU_32b/ALU_testbench.vcd
$date
	Fri Sep 24 03:19:29 2021
$end
$version
	Icarus Verilog
$end
$timescale
	1ns
$end
$scope module ALU_32b_testbench $end
$var wire 16 ! y [15:0] $end
$var reg 16 " A [15:0] $end
$var reg 16 # B [15:0] $end
$var reg 2 $ Op [1:0] $end
$var reg 1 % clk $end
$var reg 1 & reset $end
$scope module ALU1 $end
$var wire 16 ' A [15:0] $end
$var wire 16 ( B [15:0] $end
$var wire 2 ) Op [1:0] $end
$var wire 1 & clk $end
$var wire 1 * reset $end
$var reg 16 + y [15:0] $end
$upscope $end
$upscope $end
$enddefinitions $end
#0
$dumpvars
b0 +
1*
b1 )
b0 (
b0 '
x&
1%
b11 $
b0 #
b0 "
b0 !
$end
#10
0*
b0 $
b0 )
0%
#20
b1 )
1%
#25
1*
b1 $
#30
b0 )
0%
#40
b1 )
1%
#45
0*
b10 $
#50
b0 )
0%
#60
b1 )
1%
#70
b0 )
0%
#75
1*
b11 $
#80
b1 )
1%
#90
b0 )
0%
#100
b1 )
1%
#110
b0 )
0%
#120
b1 )
1%
#130
b0 )
0%
#140
b1 )
1%
#150
b0 )
0%
#160
b1 )
1%
#170
b0 )
0%
