Final_Project/Project/Multiplier_RR_ASM/src/Multiplier_RR_ASM.v
module Multiplier_RR_ASM #(parameter L_word = 4)(
                            output   [2*L_word-1:0]  product,
                            output                   Ready,
                            input    [L_word-1:0]    word1, word2,
                            input                    Start, clock, reset);
                            
  wire          Empty, Flush, Shift, Add_shift, Load_words, c_is_ws, p0;

Control_Unit M0_Controller(.Ready(Ready), .Load_words(Load_words), .Flush(Flush), .Add_shift(Add_shift), .Shift(Shift),
                           .Start(Start), .Empty(Empty), .p0(p0), .c_is_ws(c_is_ws), .clock(clock), .reset(reset));

Datapath_Unit M1_Datapath(.product(product),  .word1(word1), .word2(word2),
                                           .Load_words(Load_words), .Flush(Flush), .Add_shift(Add_shift), .Shift(Shift), .Empty(Empty), .p0(p0), .c_is_ws(c_is_ws), .clock(clock), .reset(reset));

endmodule

module Control_Unit (output Ready, 
                     output reg Load_words, Flush, Add_shift, Shift,
                     input Start, Empty, p0, c_is_ws, clock, reset);
    
        reg       state, next_state;
        parameter S_idle = 0, S_running = 1;
        assign Ready = (state == S_idle) && (!reset);
      
      always @(posedge clock, posedge reset)                       // State transitions
         if (reset == 1'b1) state <= S_idle; else state <= next_state;
      
      always @(state, Start, Empty, p0, c_is_ws) begin              // Comb logic for next state  and outputs
          Flush = 0; Load_words = 0; Shift = 0; Add_shift = 0;
        
         case (state)
             S_idle:                            if (!Start) next_state = S_idle;
                                                else if(Empty) begin next_state = S_idle; Flush = 1; end
                                                else begin Load_words = 1; next_state = S_running; end

             S_running:                         if (c_is_ws) next_state = S_idle;
                                                else if (p0) begin Add_shift = 1; next_state = S_running; end
                                                else begin Shift = 1; next_state = S_running; end
                        
            default:                                       next_state = S_idle;
         endcase
          
      end
     
endmodule

module Datapath_Unit #(parameter L_word = 4, L_count = 3)(
                        output reg [2*L_word:0] product,
                        input [L_word-1:0] word1, word2,
                        input Load_words, Flush, Add_shift, Shift, Empty, p0, c_is_ws, clock, reset);
          
          reg     [L_word-1:0]       multiplicand;
          reg     [L_count-1:0]      counter;
          assign                       Empty = (word1 == 0) || (word2 == 0);
          assign                       p0 = product[0];
          assign                       c_is_ws = (counter == L_word);
          
          
         always @(posedge clock, posedge reset)
                  if (reset == 1'b1 ) begin multiplicand <= 0; product <= 0; counter <= 0; end
                  else begin
                  if (Flush) product <= 0;
                  if (Load_words == 1)
                  begin multiplicand <= word1; product[L_word-1:0] <= word2; counter <= 0; end
                  if (Shift) begin product <= product>>1; counter <= counter + 1; end
                  if (Add_shift) begin
                      product <= {product[2*L_word:L_word] + multiplicand, product[L_word:0]}
                      >>1;
                      counter <= counter + 1;
                  end
         end

endmodule

Final_Project/Project/Multiplier_RR_ASM/test/tb_Multiplier_RR_ASM.v
`timescale 1ns/1ps
module tb_Multiplier_RR_ASM;
        parameter L_word = 4;
        wire  [2*L_word-1:0]  product;
        wire                  Ready;
        reg [L_word-1:0]  word1, word2;
        reg               Start, clock, reset;

        Multiplier_RR_ASM module1(.product(product), .Ready(Ready), .word1(word1), .word2(word2),
                                .Start(Start), .clock(clock), .reset(reset));

        initial begin
               $dumpfile("tb_Multiplier_RR_ASM.vcd");
               $dumpvars(0, tb_Multiplier_RR_ASM);
               #500 $finish;
        end
        initial begin
                    clock =1'b0;
                    forever #5 clock=~clock;
                end
                initial fork
                    #10 reset = 1;
                    #20 reset = 0;
                    #30 word1= 4'b1000; 
                    #35 word2 =  4'b1111; Start =1;
        join

endmodule

Final_Project/Project/Multiplier_RR_ASM/tb_Multiplier_RR_ASM.vcd
$date
	Mon Dec 13 18:51:41 2021
$end
$version
	Icarus Verilog
$end
$timescale
	1ps
$end
$scope module tb_Multiplier_RR_ASM $end
$var wire 8 ! product [7:0] $end
$var wire 1 " Ready $end
$var reg 1 # Start $end
$var reg 1 $ clock $end
$var reg 1 % reset $end
$var reg 4 & word1 [3:0] $end
$var reg 4 ' word2 [3:0] $end
$scope module module1 $end
$var wire 1 # Start $end
$var wire 1 $ clock $end
$var wire 1 % reset $end
$var wire 4 ( word1 [3:0] $end
$var wire 4 ) word2 [3:0] $end
$var wire 8 * product [7:0] $end
$var wire 1 + p0 $end
$var wire 1 , c_is_ws $end
$var wire 1 - Shift $end
$var wire 1 " Ready $end
$var wire 1 . Load_words $end
$var wire 1 / Flush $end
$var wire 1 0 Empty $end
$var wire 1 1 Add_shift $end
$scope module M0_Controller $end
$var wire 1 " Ready $end
$var wire 1 # Start $end
$var wire 1 $ clock $end
$var wire 1 % reset $end
$var wire 1 + p0 $end
$var wire 1 , c_is_ws $end
$var wire 1 0 Empty $end
$var reg 1 1 Add_shift $end
$var reg 1 / Flush $end
$var reg 1 . Load_words $end
$var reg 1 - Shift $end
$var reg 1 2 next_state $end
$var reg 1 3 state $end
$upscope $end
$scope module M1_Datapath $end
$var wire 1 1 Add_shift $end
$var wire 1 0 Empty $end
$var wire 1 / Flush $end
$var wire 1 . Load_words $end
$var wire 1 - Shift $end
$var wire 1 $ clock $end
$var wire 1 % reset $end
$var wire 4 4 word1 [3:0] $end
$var wire 4 5 word2 [3:0] $end
$var wire 1 + p0 $end
$var wire 1 , c_is_ws $end
$var reg 3 6 counter [2:0] $end
$var reg 4 7 multiplicand [3:0] $end
$var reg 9 8 product [8:0] $end
$upscope $end
$upscope $end
$upscope $end
$enddefinitions $end
#0
$dumpvars
bx 8
bx 7
bx 6
bx 5
bx 4
x3
02
01
x0
0/
0.
0-
x,
x+
bx *
bx )
bx (
bx '
bx &
x%
0$
1#
x"
bx !
$end
#5000
12
1.
03
1$
#10000
1.
0+
b0 !
b0 *
0,
b0 6
b0 8
b0 7
0"
0$
1%
#15000
1$
#20000
1"
0$
0%
#25000
x+
b0xxxx !
b0xxxx *
1-
0.
0"
b0xxxx 8
bx 7
13
1$
#30000
0$
b1000 &
b1000 (
b1000 4
#35000
b0xxx !
b0xxx *
b1 6
b0xxx 8
1-
00
1$
b1111 '
b1111 )
b1111 5
#40000
0$
#45000
b0xx !
b0xx *
b10 6
b0xx 8
1$
#50000
0$
#55000
b0x !
b0x *
b11 6
b0x 8
1$
#60000
0$
#65000
02
0-
0+
b0 !
b0 *
1,
b100 6
b0 8
1$
#70000
0$
#75000
12
1.
1"
03
1$
#80000
0$
#85000
11
1+
b1111 !
b1111 *
0-
0.
0"
0,
b0 6
b1111 8
b1000 7
13
1$
#90000
0$
#95000
b10000111 !
b10000111 *
b1 6
b10000111 8
1$
#100000
0$
#105000
b11 !
b11 *
b10 6
b100000011 8
1$
#110000
0$
#115000
b10000001 !
b10000001 *
b11 6
b110000001 8
1$
#120000
0$
#125000
02
01
0+
b0 !
b0 *
1,
b100 6
b0 8
1$
#130000
0$
#135000
12
1.
1"
03
1$
#140000
0$
#145000
11
1+
b1111 !
b1111 *
0-
0.
0"
0,
b0 6
b1111 8
13
1$
#150000
0$
#155000
b10000111 !
b10000111 *
b1 6
b10000111 8
1$
#160000
0$
#165000
b11 !
b11 *
b10 6
b100000011 8
1$
#170000
0$
#175000
b10000001 !
b10000001 *
b11 6
b110000001 8
1$
#180000
0$
#185000
02
01
0+
b0 !
b0 *
1,
b100 6
b0 8
1$
#190000
0$
#195000
12
1.
1"
03
1$
#200000
0$
#205000
11
1+
b1111 !
b1111 *
0-
0.
0"
0,
b0 6
b1111 8
13
1$
#210000
0$
#215000
b10000111 !
b10000111 *
b1 6
b10000111 8
1$
#220000
0$
#225000
b11 !
b11 *
b10 6
b100000011 8
1$
#230000
0$
#235000
b10000001 !
b10000001 *
b11 6
b110000001 8
1$
#240000
0$
#245000
02
01
0+
b0 !
b0 *
1,
b100 6
b0 8
1$
#250000
0$
#255000
12
1.
1"
03
1$
#260000
0$
#265000
11
1+
b1111 !
b1111 *
0-
0.
0"
0,
b0 6
b1111 8
13
1$
#270000
0$
#275000
b10000111 !
b10000111 *
b1 6
b10000111 8
1$
#280000
0$
#285000
b11 !
b11 *
b10 6
b100000011 8
1$
#290000
0$
#295000
b10000001 !
b10000001 *
b11 6
b110000001 8
1$
#300000
0$
#305000
02
01
0+
b0 !
b0 *
1,
b100 6
b0 8
1$
#310000
0$
#315000
12
1.
1"
03
1$
#320000
0$
#325000
11
1+
b1111 !
b1111 *
0-
0.
0"
0,
b0 6
b1111 8
13
1$
#330000
0$
#335000
b10000111 !
b10000111 *
b1 6
b10000111 8
1$
#340000
0$
#345000
b11 !
b11 *
b10 6
b100000011 8
1$
#350000
0$
#355000
b10000001 !
b10000001 *
b11 6
b110000001 8
1$
#360000
0$
#365000
02
01
0+
b0 !
b0 *
1,
b100 6
b0 8
1$
#370000
0$
#375000
12
1.
1"
03
1$
#380000
0$
#385000
11
1+
b1111 !
b1111 *
0-
0.
0"
0,
b0 6
b1111 8
13
1$
#390000
0$
#395000
b10000111 !
b10000111 *
b1 6
b10000111 8
1$
#400000
0$
#405000
b11 !
b11 *
b10 6
b100000011 8
1$
#410000
0$
#415000
b10000001 !
b10000001 *
b11 6
b110000001 8
1$
#420000
0$
#425000
02
01
0+
b0 !
b0 *
1,
b100 6
b0 8
1$
#430000
0$
#435000
12
1.
1"
03
1$
#440000
0$
#445000
11
1+
b1111 !
b1111 *
0-
0.
0"
0,
b0 6
b1111 8
13
1$
#450000
0$
#455000
b10000111 !
b10000111 *
b1 6
b10000111 8
1$
#460000
0$
#465000
b11 !
b11 *
b10 6
b100000011 8
1$
#470000
0$
#475000
b10000001 !
b10000001 *
b11 6
b110000001 8
1$
#480000
0$
#485000
02
01
0+
b0 !
b0 *
1,
b100 6
b0 8
1$
#490000
0$
#495000
12
1.
1"
03
1$
