asmd_Decimator/src/asmd_Decimator.v
module asmd_Decimator(output [15:0] R0,
                      input [7:0] Data, 
                      input En, Ld,
                      input clk, rst);
       wire Clr_P1_P0, Ld_P1_P0, Ld_R0; //use wire here
       Controller M0(.Clr_P1_P0(Clr_P1_P0), .Ld_P1_P0(Ld_P1_P0), .Ld_R0(Ld_R0), .En(En), .Ld(Ld), .clk(clk), .rst(rst));
       datapath_unit M1(.R0(R0), .Clr_P1_P0(Clr_P1_P0), .Ld_P1_P0(Ld_P1_P0), .Ld_R0(Ld_R0), .Data(Data), .clk(clk), .rst(rst));
endmodule


module Controller (output reg Clr_P1_P0, Ld_P1_P0, Ld_R0, 
                   input En, Ld, clk,  rst); 
parameter s_idle = 2'b00, S_1 = 2'b01,  S_full = 2'b10,  S_wait = 2'b11; 
reg [1:0]  state, next_state; 

 always @(posedge clk) 
  if (rst) state <=  s_idle; 
  else state <= next_state; 

 always @(state, En, Ld) begin 
   Clr_P1_P0 = 0; 
   Ld_P1_P0 = 0;
   Ld_R0 = 0;

     case(state) 
         s_idle: if (En) begin next_state = S_1; Ld_P1_P0 = 1; end 
                 else next_state = s_idle; 

         S_1:    begin next_state = S_full; Ld_P1_P0 = 1; end 

         S_full: if (!Ld) begin next_state = S_wait; Ld_R0 = 1; end 
            else if (En) begin next_state = S_1;  Ld_P1_P0 = 1; end 
            else begin next_state = s_idle; Clr_P1_P0 = 1; end 

        S_wait: if (!Ld) next_state = S_wait; 
            else begin  
              Ld_R0 = 1; 
            if (En) begin Ld_P1_P0 = 1; next_state = S_1; end 
            else begin next_state = s_idle; Clr_P1_P0 = 1; end 
            end  
        default: next_state = s_idle;  
     endcase
 end
endmodule


module datapath_unit (output reg [15:0] R0,
                      input [7:0] Data, 
                      input  Clr_P1_P0, Ld_P1_P0, Ld_R0,
                      input clk, rst);
    reg [7:0]  P0, P1;
    
    always@(posedge clk, posedge rst)
        if (rst == 1'b1) begin
            P1 <= 8'b0;
            P0 <= 0;
        end
        else begin
      
        if (Clr_P1_P0 == 1) begin
            P1 <= 0;
            P0 <= 0;
        end
           
        else if (Ld_P1_P0) begin
          P1 <= Data;
          P0 <= P1; // P1->P0
       end   
        else if (Ld_R0) begin
            R0 <= 16'h70;
        end
            
       
    end
endmodule

asmd_Decimator/test/tb_asmd_Decimator.v
`timescale 1ns/1ps
module tb_asmd_Decimator;
        reg clk, rst;
        reg En, Ld;
        reg [7:0] Data;
        wire [15:0] R0;

        asmd_Decimator module1(.R0(R0), .clk(clk), .rst(rst), .Data(Data), .En(En), .Ld(Ld));
                               
                               
        initial
            begin
               $dumpfile("tb_asmd_Decimator.vcd");
               $dumpvars(0, tb_asmd_Decimator);
               #200 $finish;
            end
        initial begin
            clk =1'b0;
            forever #5 clk=~clk;
        end
        initial fork
            #10 rst = 1'b1;
            #15 rst = 1'b0;
            
            #20 En = 1'b0;
            #25 Ld = 1'b0;
            
            #30 En = 1'b1;
            #40 Ld = 1'b0; Data = 8'h80;
           
        join


endmodule

asmd_Decimator/tb_asmd_Decimator.vcd
$date
	Fri Oct  8 03:30:17 2021
$end
$version
	Icarus Verilog
$end
$timescale
	1ps
$end
$scope module tb_asmd_Decimator $end
$var wire 16 ! R0 [15:0] $end
$var reg 8 " Data [7:0] $end
$var reg 1 # En $end
$var reg 1 $ Ld $end
$var reg 1 % clk $end
$var reg 1 & rst $end
$scope module module1 $end
$var wire 8 ' Data [7:0] $end
$var wire 1 # En $end
$var wire 1 $ Ld $end
$var wire 1 % clk $end
$var wire 1 & rst $end
$var wire 16 ( R0 [15:0] $end
$var wire 1 ) Ld_R0 $end
$var wire 1 * Ld_P1_P0 $end
$var wire 1 + Clr_P1_P0 $end
$scope module M0 $end
$var wire 1 # En $end
$var wire 1 $ Ld $end
$var wire 1 % clk $end
$var wire 1 & rst $end
$var reg 1 + Clr_P1_P0 $end
$var reg 1 * Ld_P1_P0 $end
$var reg 1 ) Ld_R0 $end
$var reg 2 , next_state [1:0] $end
$var reg 2 - state [1:0] $end
$upscope $end
$scope module M1 $end
$var wire 1 + Clr_P1_P0 $end
$var wire 8 . Data [7:0] $end
$var wire 1 * Ld_P1_P0 $end
$var wire 1 ) Ld_R0 $end
$var wire 1 % clk $end
$var wire 1 & rst $end
$var reg 8 / P0 [7:0] $end
$var reg 8 0 P1 [7:0] $end
$var reg 16 1 R0 [15:0] $end
$upscope $end
$upscope $end
$upscope $end
$enddefinitions $end
#0
$dumpvars
bx 1
bx 0
bx /
b10000000 .
bx -
bx ,
x+
x*
x)
bx (
b10000000 '
x&
0%
x$
x#
b10000000 "
bx !
$end
#5000
1%
#10000
b0 /
b0 0
0%
1&
#15000
1%
0&
#20000
b0 ,
0)
0*
0+
0%
0#
#25000
b0 -
1%
0$
#30000
1*
b1 ,
0%
1#
#35000
b10 ,
1*
b1 -
b10000000 0
1%
#40000
0%
#45000
1)
b11 ,
0*
b10 -
b10000000 /
1%
#50000
0%
#55000
0)
b11 -
b1110000 !
b1110000 (
b1110000 1
1%
