Final_Project/Project/Multiplier_STG_0/src/Multiplier_STG_0.v
module Multiplier_STG_0 #(parameter L_word = 4)
                         (output [2*L_word-1:0] product,
                          output                  Ready,
                          input [L_word-1:0] word1, word2,
                          input Start, clock, reset);

wire        m0, Load_words, Shift;

Control_Unit M0_Controller (.Load_words(Load_words), .Shift(Shift), .Add(Add), .Ready(Ready), .m0(m0), .Start(Start), .clock(clock), .reset(reset));

Datapath_Unit M1_Datapath (.product(product), .m0(m0), .word1(word1), .word2(word2), .Load_words(Load_words), .Shift(Shift), .Add(Add), .clock(clock), .reset(reset));
endmodule

module Control_Unit #(parameter L_word = 4, L_state = 4)     //Datapath size, state
                                                              
                     (output reg              Load_words, Shift, Add,
                      output                  Ready,
                      input                   m0, Start, clock, reset);

              reg    [L_state-1:0]          state, next_state;
              parameter                     S_idle = 0, S_1 = 1, S_2 = 2,
                                            S_3 = 3, S_4 = 4, S_5 = 5, S_6 = 6,
                                            S_7 = 7, S_8 = 8;
      assign                                Ready = ((state == S_idle) && !reset)
                                                   || (state == S_8);
always @(posedge clock, posedge reset)     // State transitions

    if (reset == 1'b1) state <= S_idle; else state <= next_state;

always @(state, Start, m0) begin     // Next state and control logic
       Load_words = 0; Shift = 0; Add = 0;  // Default values
  case(state)

      S_idle:                           if (Start) begin Load_words = 1; next_state = S_1; end
                                        else next_state = S_idle;

      S_1:                              if(m0)    begin Add = 1; next_state = S_2; end
                                        else      begin Shift = 1; next_state = S_3; end
      S_2:                                        begin Shift = 1; next_state = S_3; end

      S_3:                              if(m0)    begin Add = 1; next_state = S_4; end
                                        else      begin Shift = 1; next_state = S_5; end
      S_4:                                        begin Shift = 1; next_state = S_5; end
                         
      S_5:                              if(m0)    begin Add = 1; next_state = S_6; end
                                        else      begin Shift = 1; next_state = S_7; end
      S_6:                                        begin Shift = 1; next_state = S_7; end

      S_7:                              if(m0)    begin Add = 1; next_state = S_8; end
                                        else      begin next_state = S_8; end
                                 
      S_8:                              if(Start) begin Load_words = 1; next_state = S_1; end
                                       else next_state = S_8;
                        default             next_state = S_idle;
  endcase
end
endmodule

module Datapath_Unit #(parameter L_word = 4)( 
                       output reg   [2*L_word-1:0]   product,
                       output                        m0,
                       input        [L_word-1:0]     word1, word2,
                       input                         Load_words, Shift, Add, clock, reset);

   reg  [2*L_word-1:0]    multiplicand;
   reg  [L_word-1:0]      multiplier;

   assign                 m0 = multiplier[0];
                   
                   //Register/Datapath Operations

always @(posedge clock, posedge reset) begin
         if   (reset == 1'b1 ) begin multiplier <= 0; multiplicand <= 0; product <= 0; end
         else if (Load_words == 1'b1 ) begin 
              multiplicand <= word1 ;
              multiplier <= word2; product <= 0;
         end
         else if (Shift == 1'b1) product <= product + multiplicand;
end
endmodule

Final_Project/Project/Multiplier_STG_0/test/tb_Multiplier_STG_0.v
`timescale 1ns/1ps
module tb_Multiplier_STG_0;
        parameter L_word = 4;
        wire  [2*L_word-1:0]  product;
        wire                  Ready;
        reg    [L_word-1:0]   word1, word2;
        reg                   Start, clock, reset;

        Multiplier_STG_0 module1(.product(product), .Ready(Ready), .word1(word1), .word2(word2),
                                .Start(Start), .clock(clock), .reset(reset));

        initial begin
               $dumpfile("tb_Multiplier_STG_0.vcd");
               $dumpvars(0, tb_Multiplier_STG_0);
               #500 $finish;
        end
        initial begin
                    clock =1'b0;
                    forever #5 clock=~clock;
                end
                initial fork
                    #10 reset = 1;
                    #20 reset = 0;
                    #30 word1= 4'b1000; word2 =  4'b1111; Start =1;
        join

endmodule

Final_Project/Project/Multiplier_STG_0/tb_Multiplier_STG_0.vcd
$date
	Tue Dec 14 02:23:35 2021
$end
$version
	Icarus Verilog
$end
$timescale
	1ps
$end
$scope module tb_Multiplier_STG_0 $end
$var wire 8 ! product [7:0] $end
$var wire 1 " Ready $end
$var reg 1 # Start $end
$var reg 1 $ clock $end
$var reg 1 % reset $end
$var reg 4 & word1 [3:0] $end
$var reg 4 ' word2 [3:0] $end
$scope module module1 $end
$var wire 1 # Start $end
$var wire 1 $ clock $end
$var wire 1 % reset $end
$var wire 4 ( word1 [3:0] $end
$var wire 4 ) word2 [3:0] $end
$var wire 8 * product [7:0] $end
$var wire 1 + m0 $end
$var wire 1 , Shift $end
$var wire 1 " Ready $end
$var wire 1 - Load_words $end
$var wire 1 . Add $end
$scope module M0_Controller $end
$var wire 1 " Ready $end
$var wire 1 # Start $end
$var wire 1 $ clock $end
$var wire 1 % reset $end
$var wire 1 + m0 $end
$var reg 1 . Add $end
$var reg 1 - Load_words $end
$var reg 1 , Shift $end
$var reg 4 / next_state [3:0] $end
$var reg 4 0 state [3:0] $end
$upscope $end
$scope module M1_Datapath $end
$var wire 1 . Add $end
$var wire 1 - Load_words $end
$var wire 1 , Shift $end
$var wire 1 $ clock $end
$var wire 1 % reset $end
$var wire 4 1 word1 [3:0] $end
$var wire 4 2 word2 [3:0] $end
$var wire 1 + m0 $end
$var reg 8 3 multiplicand [7:0] $end
$var reg 4 4 multiplier [3:0] $end
$var reg 8 5 product [7:0] $end
$upscope $end
$upscope $end
$upscope $end
$enddefinitions $end
#0
$dumpvars
bx 5
bx 4
bx 3
b1111 2
bx 1
bx 0
b0 /
0.
0-
0,
x+
bx *
b1111 )
bx (
b1111 '
bx &
x%
0$
1#
x"
bx !
$end
#5000
b1 /
1-
b0 0
1$
#10000
1-
0+
b0 !
b0 *
b0 5
b0 3
b0 4
0"
0$
1%
#15000
1$
#20000
1"
0$
0%
#25000
1.
0"
1+
b10 /
0,
0-
b1111 4
b0xxxx 3
b1 0
1$
#30000
0$
b1000 &
b1000 (
b1000 1
#35000
b11 /
1,
0.
b10 0
1$
#40000
0$
#45000
b100 /
1.
0,
bx !
bx *
bx 5
b11 0
1$
#50000
0$
#55000
b101 /
1,
0.
b100 0
1$
#60000
0$
#65000
b110 /
1.
0,
b101 0
1$
#70000
0$
#75000
b111 /
1,
0.
b110 0
1$
#80000
0$
#85000
b1000 /
1.
0,
b111 0
1$
#90000
0$
#95000
b1 /
1-
0.
1"
b1000 0
1$
#100000
0$
#105000
b10 /
1.
0-
0"
b0 !
b0 *
b0 5
b1000 3
b1 0
1$
#110000
0$
#115000
b11 /
1,
0.
b10 0
1$
#120000
0$
#125000
b100 /
1.
0,
b1000 !
b1000 *
b1000 5
b11 0
1$
#130000
0$
#135000
b101 /
1,
0.
b100 0
1$
#140000
0$
#145000
b110 /
1.
0,
b10000 !
b10000 *
b10000 5
b101 0
1$
#150000
0$
#155000
b111 /
1,
0.
b110 0
1$
#160000
0$
#165000
b1000 /
1.
0,
b11000 !
b11000 *
b11000 5
b111 0
1$
#170000
0$
#175000
b1 /
1-
0.
1"
b1000 0
1$
#180000
0$
#185000
b10 /
1.
0-
0"
b0 !
b0 *
b0 5
b1 0
1$
#190000
0$
#195000
b11 /
1,
0.
b10 0
1$
#200000
0$
#205000
b100 /
1.
0,
b1000 !
b1000 *
b1000 5
b11 0
1$
#210000
0$
#215000
b101 /
1,
0.
b100 0
1$
#220000
0$
#225000
b110 /
1.
0,
b10000 !
b10000 *
b10000 5
b101 0
1$
#230000
0$
#235000
b111 /
1,
0.
b110 0
1$
#240000
0$
#245000
b1000 /
1.
0,
b11000 !
b11000 *
b11000 5
b111 0
1$
#250000
0$
#255000
b1 /
1-
0.
1"
b1000 0
1$
#260000
0$
#265000
b10 /
1.
0-
0"
b0 !
b0 *
b0 5
b1 0
1$
#270000
0$
#275000
b11 /
1,
0.
b10 0
1$
#280000
0$
#285000
b100 /
1.
0,
b1000 !
b1000 *
b1000 5
b11 0
1$
#290000
0$
#295000
b101 /
1,
0.
b100 0
1$
#300000
0$
#305000
b110 /
1.
0,
b10000 !
b10000 *
b10000 5
b101 0
1$
#310000
0$
#315000
b111 /
1,
0.
b110 0
1$
#320000
0$
#325000
b1000 /
1.
0,
b11000 !
b11000 *
b11000 5
b111 0
1$
#330000
0$
#335000
b1 /
1-
0.
1"
b1000 0
1$
#340000
0$
#345000
b10 /
1.
0-
0"
b0 !
b0 *
b0 5
b1 0
1$
#350000
0$
#355000
b11 /
1,
0.
b10 0
1$
#360000
0$
#365000
b100 /
1.
0,
b1000 !
b1000 *
b1000 5
b11 0
1$
#370000
0$
#375000
b101 /
1,
0.
b100 0
1$
#380000
0$
#385000
b110 /
1.
0,
b10000 !
b10000 *
b10000 5
b101 0
1$
#390000
0$
#395000
b111 /
1,
0.
b110 0
1$
#400000
0$
#405000
b1000 /
1.
0,
b11000 !
b11000 *
b11000 5
b111 0
1$
#410000
0$
#415000
b1 /
1-
0.
1"
b1000 0
1$
#420000
0$
#425000
b10 /
1.
0-
0"
b0 !
b0 *
b0 5
b1 0
1$
#430000
0$
#435000
b11 /
1,
0.
b10 0
1$
#440000
0$
#445000
b100 /
1.
0,
b1000 !
b1000 *
b1000 5
b11 0
1$
#450000
0$
#455000
b101 /
1,
0.
b100 0
1$
#460000
0$
#465000
b110 /
1.
0,
b10000 !
b10000 *
b10000 5
b101 0
1$
#470000
0$
#475000
b111 /
1,
0.
b110 0
1$
#480000
0$
#485000
b1000 /
1.
0,
b11000 !
b11000 *
b11000 5
b111 0
1$
#490000
0$
#495000
b1 /
1-
0.
1"
b1000 0
1$
